asl_utility/__init__.py
asl_utility/arg_helpers.py
asl_utility/np_helpers.py
asl_utility/tf_helpers.py
asl_utility/transform_helpers/_ArrayLike.py
asl_utility/transform_helpers/_CartesianPose.py
asl_utility/transform_helpers/_CartesianPosition.py
asl_utility/transform_helpers/_JointPose.py
asl_utility/transform_helpers/_Quaternion.py
asl_utility/transform_helpers/_Transformation.py
asl_utility/transform_helpers/_TransformationComponents.py
asl_utility/transform_helpers/_Vector3.py
asl_utility/transform_helpers/_Vector3Like.py
asl_utility/transform_helpers/__init__.py
asl_utility-1.1.0.dist-info/LICENSE
asl_utility-1.1.0.dist-info/METADATA
asl_utility-1.1.0.dist-info/WHEEL
asl_utility-1.1.0.dist-info/top_level.txt
asl_utility-1.1.0.dist-info/RECORD
