Metadata-Version: 2.1
Name: asl-utility
Version: 1.1.0
Summary: Utility components for numpy, math and transformations.
Author: Autonomous Systems Lab
Author-email: Fabian Schreier <fabian.schreier@festo.com>
Project-URL: Repository, https://gitlab.com/autonomous-systems-lab/libraries/asl-utility
Project-URL: Changelog, https://gitlab.com/autonomous-systems-lab/libraries/asl-utility/-/blob/main/CHANGELOG.md
Classifier: Programming Language :: Python :: 3
Classifier: License :: OSI Approved :: MIT License
Classifier: Operating System :: OS Independent
Requires-Python: >=3.7
License-File: LICENSE
Requires-Dist: numpy >=1.21.0
Requires-Dist: typing-extensions >=4.0.0
Requires-Dist: Deprecated
Provides-Extra: linting
Requires-Dist: flake8 ; extra == 'linting'
Requires-Dist: flake8-pyproject ; extra == 'linting'
Requires-Dist: flake8-formatter-junit-xml ; extra == 'linting'
Provides-Extra: test
Requires-Dist: pytest ; extra == 'test'
Requires-Dist: scipy ; extra == 'test'
